validproxy/__init__.py
validproxy/proxy_checker.py
validproxy-2.0.0.dist-info/LICENSE
validproxy-2.0.0.dist-info/METADATA
validproxy-2.0.0.dist-info/WHEEL
validproxy-2.0.0.dist-info/top_level.txt
validproxy-2.0.0.dist-info/RECORD
