Metadata-Version: 2.1
Name: validproxy
Version: 2.0.0
Summary: A package to check the validity of proxies.
Home-page: https://mrfidal.in/cyber-security/validproxy
Author: Fidal
Author-email: mrfidal@proton.me
Classifier: Programming Language :: Python :: 3
Classifier: License :: OSI Approved :: MIT License
Classifier: Operating System :: OS Independent
Requires-Python: >=3.6
License-File: LICENSE
Requires-Dist: requests
